utils_mystuff_windows/__init__.py
utils_mystuff_windows/utils_win32.py
utils_mystuff_windows/version.py
utils_mystuff_windows-1.0.0.dist-info/METADATA
utils_mystuff_windows-1.0.0.dist-info/WHEEL
utils_mystuff_windows-1.0.0.dist-info/licenses/AUTHORS.md
utils_mystuff_windows-1.0.0.dist-info/licenses/LICENSE.txt
utils_mystuff_windows-1.0.0.dist-info/RECORD
