Metadata-Version: 2.4
Name: utils-mystuff-windows
Version: 1.0.0
Summary: Package with various utilities depending on windows platform i. e. windows handling
Project-URL: Documentation, https://dornech.github.io/utils-mystuff-windows
Project-URL: Source, https://github.com/dornech/utils-mystuff-windows
Project-URL: Tracker, https://github.com/dornech/utils-mystuff-windows/issues
Project-URL: Sponsor, https://github.com/sponsors/dornech
Author-email: dornech <dornech@gmx.de>
License: GPL-3.0-only
License-File: AUTHORS.md
License-File: LICENSE.txt
Keywords: Win32,windows handling
Classifier: Programming Language :: Python
Classifier: Programming Language :: Python :: 3.9
Classifier: Programming Language :: Python :: 3.10
Classifier: Programming Language :: Python :: 3.11
Classifier: Programming Language :: Python :: 3.12
Classifier: Programming Language :: Python :: 3.13
Classifier: Programming Language :: Python :: Implementation :: CPython
Requires-Python: >=3.9
Requires-Dist: pywin32
